datafog_instructor/__init__.py
datafog_instructor/core.py
datafog_instructor/models.py
datafog_instructor/utils.py
datafog_instructor-0.1.0b4.dist-info/LICENSE
datafog_instructor-0.1.0b4.dist-info/METADATA
datafog_instructor-0.1.0b4.dist-info/WHEEL
datafog_instructor-0.1.0b4.dist-info/top_level.txt
datafog_instructor-0.1.0b4.dist-info/RECORD
