Metadata-Version: 2.1
Name: datafog-instructor
Version: 0.1.0b4
Summary: Scan, redact, and manage PII in your documents before they get uploaded to a Retrieval Augmented Generation (RAG) system.
Home-page: https://datafog.ai
Author: Sid Mohan
Author-email: sid@datafog.ai
Maintainer: DataFog
Maintainer-email: hi@datafog.ai
License: MIT
Project-URL: Homepage, https://datafog.ai
Project-URL: Documentation, https://docs.datafog.ai
Project-URL: Discord, https://discord.gg/bzDth394R4
Project-URL: Twitter, https://twitter.com/datafoginc
Project-URL: GitHub, https://github.com/datafog/datafog-python
Keywords: pii,redaction,nlp,rag,retrieval augmented generation
Classifier: Programming Language :: Python :: 3.10
Classifier: Programming Language :: Python :: 3.11
Classifier: License :: OSI Approved :: MIT License
Classifier: Operating System :: OS Independent
Classifier: Framework :: tox
Classifier: Framework :: Pytest
Classifier: Intended Audience :: Developers
Classifier: Intended Audience :: Science/Research
Classifier: Intended Audience :: Information Technology
Classifier: Intended Audience :: System Administrators
Requires-Python: >=3.10
License-File: LICENSE
Requires-Dist: pydantic
Requires-Dist: ollama
Requires-Dist: ollama-instructor
Requires-Dist: python-dotenv
